LICENSE.txt
MANIFEST.in
README.rst
setup.cfg
setup.py
docs/Makefile
docs/changes.rst
docs/conf.py
docs/func.rst
docs/index.rst
docs/types.rst
docs/upgrade.rst
src/s4u/__init__.py
src/s4u.sqlalchemy.egg-info/PKG-INFO
src/s4u.sqlalchemy.egg-info/SOURCES.txt
src/s4u.sqlalchemy.egg-info/dependency_links.txt
src/s4u.sqlalchemy.egg-info/namespace_packages.txt
src/s4u.sqlalchemy.egg-info/not-zip-safe
src/s4u.sqlalchemy.egg-info/requires.txt
src/s4u.sqlalchemy.egg-info/top_level.txt
src/s4u/sqlalchemy/__init__.py
src/s4u/sqlalchemy/array.py
src/s4u/sqlalchemy/func.py
src/s4u/sqlalchemy/inet.py
src/s4u/sqlalchemy/json.py
src/s4u/sqlalchemy/mapping.py
src/s4u/sqlalchemy/meta.py
src/s4u/sqlalchemy/testing.py
src/s4u/sqlalchemy/uuid.py
src/s4u/sqlalchemy/tests/__init__.py
src/s4u/sqlalchemy/tests/test_array.py
src/s4u/sqlalchemy/tests/test_func.py
src/s4u/sqlalchemy/tests/test_inet.py
src/s4u/sqlalchemy/tests/test_json.py
src/s4u/sqlalchemy/tests/test_mapping.py
src/s4u/sqlalchemy/tests/test_testing.py
src/s4u/sqlalchemy/tests/test_uuid.py